hypermodern_python_example/__init__.py
hypermodern_python_example/console.py
hypermodern_python_example/wikipedia.py
hypermodern_python_example-0.1.0.dist-info/entry_points.txt
hypermodern_python_example-0.1.0.dist-info/LICENSE
hypermodern_python_example-0.1.0.dist-info/WHEEL
hypermodern_python_example-0.1.0.dist-info/METADATA
hypermodern_python_example-0.1.0.dist-info/RECORD
